allrucodes/__init__.py
allrucodes/basecodes.py
allrucodes/data/okopf.json
allrucodes/data/okopf.pkl
allrucodes/data/oksm.pkl
allrucodes/okopf.py
allrucodes/oksm.py
allrucodes-0.1.1.dist-info/LICENSE
allrucodes-0.1.1.dist-info/WHEEL
allrucodes-0.1.1.dist-info/METADATA
allrucodes-0.1.1.dist-info/RECORD
