Metadata-Version: 2.1
Name: allrucodes
Version: 0.1.1
Summary: Python package with a collection of official all-russian codes catalogs.
Home-page: https://github.com/naydyonov/allrucodes
License: MIT
Author: Alexey Naydyonov
Requires-Python: >=3.8,<4.0
Classifier: Development Status :: 2 - Pre-Alpha
Classifier: Intended Audience :: Developers
Classifier: License :: OSI Approved :: MIT License
Classifier: Natural Language :: English
Classifier: Programming Language :: Python :: 3
Classifier: Programming Language :: Python :: 3.10
Classifier: Programming Language :: Python :: 3.6
Classifier: Programming Language :: Python :: 3.7
Classifier: Programming Language :: Python :: 3.8
Classifier: Programming Language :: Python :: 3.9
Requires-Dist: fuzzywuzzy (>=0.18.0,<0.19.0)
Requires-Dist: numpy (>=1.22.3,<2.0.0)
